jn_skey/__init__.py
jn_skey/jn-skey copy.py
jn_skey/jn-skey.py
jn_skey/jn_skey.py
jn_skey-1.0.7.dist-info/LICENSE
jn_skey-1.0.7.dist-info/METADATA
jn_skey-1.0.7.dist-info/WHEEL
jn_skey-1.0.7.dist-info/entry_points.txt
jn_skey-1.0.7.dist-info/top_level.txt
jn_skey-1.0.7.dist-info/RECORD
